{
    "a2aDes":"threeDes",
    "accoucheShookhands":"shookhands",
    "actionWaydown":"waydown",
    "activeWitheveryone":"witheveryone",
    "analphabeticLaceyfamily":"laceyfamily",
    "arrayGraciously":"graciously",
    "arrayMsg":"face_msg",
    "attributeFondest":"fondest",
    "characterListening":"listening",
    "cilInastonishment":"inastonishment",
    "dachshundOfdarrell":"ofdarrell",
    "dacianLikes":"likes",
    "dacoitData":"rightData",
    "dacoityGotany":"gotany",
    "demarshalAnexciting":"anexciting",
    "dereferenceGlowering":"glowering",
    "dhtmlGirlswaved":"girlswaved",
    "dirtyBeenwaiting":"beenwaiting",
    "dirtyWillingly":"willingly",
    "eagerlyReal":"isReal",
    "eaglewoodType":"upType",
    "eagreDefinite":"definite",
    "enumLeads":"leads",
    "equalityUserphone":"userphone",
    "equivalenceData":"responseData",
    "fableIreally":"ireally",
    "fabricateBegnning":"begnning",
    "fontEyebrows":"eyebrows",
    "gabelleDrawing":"drawing",
    "generatingRoad":"road",
    "guiReplies":"replies",
    "hamiltonianVanished":"vanished",
    "hostAbaby":"ababy",
    "iacuHugsand":"hugsand",
    "immutableFond":"fond",
    "indexAuh":"isAuh",
    "jacamarGoodphotograph":"goodphotograph",
    "kabobPatiently":"patiently",
    "labellumTheselfishness":"theselfishness",
    "labelNotice":"isReyNotice",
    "labialiseExercises":"exercises",
    "libertineExpected":"expected",
    "libidinalPop":"isPopLw",
    "libidinousBless":"bless",
    "libidinousMsg":"id_front_msg",
    "libidinousMurmuredsomething":"murmuredsomething",
    "libranAtgwendoline":"atgwendoline",
    "libranCove":"cove",
    "librationBushes":"bushes",
    "linearCalling":"calling",
    "loginBelievethem":"believethem",
    "macadamPlates":"plates",
    "managedRecovered":"recovered",
    "matrixQcd":"MnCWMZQBwLc",
    "memoryBiggerand":"biggerand",
    "moduleListened":"listened",
    "multiuserDescribing":"describing",
    "nabeOfyourletters":"ofyourletters",
    "nabobshipYell":"yell",
    "nabokovianGlowing":"glowing",
    "parameterizeComeout":"comeout",
    "partialMsg":"isReyNoticeMsg",
    "partialSheplunged":"sheplunged",
    "pdaAttennis":"attennis",
    "pdaIsemily":"isemily",
    "platformInterfering":"interfering",
    "qandaharDarrelp":"darrelp",
    "qbasicFiveminutes":"fiveminutes",
    "rabbathKisses":"kisses",
    "refactoringWithcolour":"withcolour",
    "retrieveConcerned":"concerned",
    "sabaeanStuff":"stuff",
    "sabaismMode":"loan_mode",
    "sabJoking":"joking",
    "satisfiabilitySymbol":"symbol",
    "savepointAdored":"adored",
    "searchingDelicate":"delicate",
    "serializationSallyhope":"sallyhope",
    "sexagesimalVoiceand":"voiceand",
    "sharedStuffing":"stuffing",
    "tabardOutspoken":"outspoken",
    "tabascoNumber":"idNumber",
    "tabefactionBeyond":"beyond",
    "travelingWildly":"wildly",
    "uarDarnell":"darnell",
    "uartHark":"hark",
    "underflowEscape":"escape",
    "vacationistLaceyor":"laceyor",
    "vowelDareto":"dareto",
    "wackeExasperating":"exasperating",
    "wackoFurious":"furious",
    "wadableSmessage":"smessage",
    "wadableStatus":"certStatus",
    "wadAmused":"amused",
    "wizardThisto":"thisto",
    "wrapperAndsally":"andsally",
    "xanthiumShetruly":"shetruly",
    "xsltIntensly":"intensly",
    "yabbiDiff":"diffId",
    "yabbiOwnparty":"ownparty",
    "yabbyOpening":"opening",
    "zaftigTwinkle":"twinkle",
    "zaguanAndwas":"andwas",
    "actionWizard":"wizard"
}
